pysimibot/__init__.py
pysimibot/pysimibot.py
pysimibot-0.1.0.dist-info/entry_points.txt
pysimibot-0.1.0.dist-info/WHEEL
pysimibot-0.1.0.dist-info/METADATA
pysimibot-0.1.0.dist-info/RECORD
